{"sections":{"main":{"type":"main-page","disabled":true,"settings":{}},"16381679244a4c20cf":{"type":"image-row","blocks":{"2e3d1bea-3908-4933-9b8a-31fa9bd2be39":{"type":"image","settings":{"image":"shopify:\/\/shop_images\/Screen_Shot_2022-03-09_at_1.18.32_PM.jpg","image_link":"","text":"","overlay":false}}},"block_order":["2e3d1bea-3908-4933-9b8a-31fa9bd2be39"],"settings":{"space_around":true,"full_width":true,"space_around_block":false,"space_around_mobile":false,"half":false,"stack_mobile":false,"hide_mobile":false,"hide_desktop":false}},"164359834612c33f88":{"type":"rich-text","disabled":true,"blocks":{"1643598346c450cffe-0":{"type":"heading","disabled":true,"settings":{"title":"Rich text"}},"1643598346c450cffe-1":{"type":"text","settings":{"enlarge_text":true,"text":"<p>Complement your core wardrobe to ensure you are in style. Feel great in your clothes every day and be well-dressed for any occasion. Lorem ipsum dolor sit amet, consectetur adipiscing elit. Donec convallis elit nec elementum accumsan. Donec posuere a quam ac sollicitudin.<\/p>"}}},"block_order":["1643598346c450cffe-0","1643598346c450cffe-1"],"settings":{"align_text":"center","narrow_column":true,"divider":false}},"1643596686ebd89cef":{"type":"spacer","disabled":true,"settings":{"spacer_size":"medium"}},"164359843140a3d5cd":{"type":"image-row","blocks":{"0464daf3-d94a-4065-8d95-0a8399ba9af2":{"type":"image","settings":{"image":"shopify:\/\/shop_images\/965620-White_4_900x_c400c2fb-203f-4089-93d2-8499fc697977.webp","image_link":"shopify:\/\/collections\/fathers-day","text":"Father's Day","overlay":true}},"6789a995-f0c7-445b-8b4b-6469ce8ce888":{"type":"image","settings":{"image":"shopify:\/\/shop_images\/963771-Navy_Blue_4.jpg","image_link":"shopify:\/\/collections\/cozy","text":"Cozy","overlay":true}},"518a68fd-9cc2-4180-8979-bec34c14d826":{"type":"image","settings":{"image":"shopify:\/\/shop_images\/959514-Navy_Blue_2_900x_a1a2e767-1c59-406e-b923-b5cd06b354a6.webp","image_link":"shopify:\/\/collections\/office","text":"Office","overlay":true}}},"block_order":["0464daf3-d94a-4065-8d95-0a8399ba9af2","6789a995-f0c7-445b-8b4b-6469ce8ce888","518a68fd-9cc2-4180-8979-bec34c14d826"],"settings":{"space_around":true,"full_width":true,"space_around_block":true,"space_around_mobile":true,"half":false,"stack_mobile":true,"hide_mobile":false,"hide_desktop":false}},"16435988837b731f6a":{"type":"image-row","blocks":{"23b9a25d-4d2c-4c2e-a046-c8faf2cf07b3":{"type":"image","settings":{"image":"shopify:\/\/shop_images\/963602-Black_5_900x_ebbbfa3a-64d8-42ab-a64e-076530b4ad66.webp","image_link":"shopify:\/\/collections\/casual","text":"Casual","overlay":true}},"5d74cbbb-6490-46f2-b9ff-1d0b57b13b8b":{"type":"image","settings":{"image":"shopify:\/\/shop_images\/964062-NavyBlue-7_1800x1800_b7b36f5e-3150-49e0-b5a5-2d6c48c33927.webp","image_link":"shopify:\/\/collections\/date","text":"Date","overlay":true}},"a8c7c9d7-6033-4f5e-8aa7-2c655a842dcb":{"type":"image","settings":{"image":"shopify:\/\/shop_images\/965912-Gray_6_900x_773ef009-9435-4d36-b844-313d7c9cc72c.webp","image_link":"shopify:\/\/collections\/street-1","text":"Street","overlay":true}}},"block_order":["23b9a25d-4d2c-4c2e-a046-c8faf2cf07b3","5d74cbbb-6490-46f2-b9ff-1d0b57b13b8b","a8c7c9d7-6033-4f5e-8aa7-2c655a842dcb"],"settings":{"space_around":true,"full_width":true,"space_around_block":true,"space_around_mobile":true,"half":false,"stack_mobile":true,"hide_mobile":false,"hide_desktop":false}},"164359862541e99828":{"type":"image-row","blocks":{"61eea861-9ec8-4c02-a6a1-ccc5566fc386":{"type":"image","settings":{"image":"shopify:\/\/shop_images\/962662-Sand_4_900x_ec144106-4c73-4dc2-ab88-fed3dda9be68.webp","image_link":"shopify:\/\/collections\/korean","text":"Korean","overlay":true}},"1981e154-0f5c-4e30-9bbc-32e45b6ae60b":{"type":"image","settings":{"image":"shopify:\/\/shop_images\/961113-Black_4_900x_461ce05d-1191-4d82-9589-7a3bc4231fc3.webp","image_link":"shopify:\/\/collections\/party","text":"Party","overlay":true}},"0a907218-a049-4f58-9a41-a0fb78f4e37b":{"type":"image","settings":{"image":"shopify:\/\/shop_images\/965081-Plum_4_900x_0dc680ad-b3cc-4145-9418-cbb0d88f9748.webp","image_link":"shopify:\/\/collections\/lounge","text":"Loungewear","overlay":true}}},"block_order":["61eea861-9ec8-4c02-a6a1-ccc5566fc386","1981e154-0f5c-4e30-9bbc-32e45b6ae60b","0a907218-a049-4f58-9a41-a0fb78f4e37b"],"settings":{"space_around":true,"full_width":true,"space_around_block":true,"space_around_mobile":true,"half":false,"stack_mobile":true,"hide_mobile":false,"hide_desktop":false}},"1643598277f79f2d0c":{"type":"spacer","disabled":true,"settings":{"spacer_size":"medium"}}},"order":["main","16381679244a4c20cf","164359834612c33f88","1643596686ebd89cef","164359843140a3d5cd","16435988837b731f6a","164359862541e99828","1643598277f79f2d0c"]}